Metadata-Version: 2.1
Name: pyParkO
Version: 0.0.2
Summary: pyParkO is a Python-based implementation of the Parker-Oldenburg Algorithm for calculating gravity anomalies from a density interface and recovering the density interface from gravity anomalies.
Author: ZengJH
Author-email: z1714833751@163.com
Requires-Python: >=3.6
License-File: LICENSE
